sphinx_autodoc_napoleon_typehints.py
sphinx_autodoc_napoleon_typehints-2.1.6.dist-info/DESCRIPTION.rst
sphinx_autodoc_napoleon_typehints-2.1.6.dist-info/METADATA
sphinx_autodoc_napoleon_typehints-2.1.6.dist-info/RECORD
sphinx_autodoc_napoleon_typehints-2.1.6.dist-info/WHEEL
sphinx_autodoc_napoleon_typehints-2.1.6.dist-info/metadata.json
sphinx_autodoc_napoleon_typehints-2.1.6.dist-info/top_level.txt
sphinx_autodoc_napoleon_typehints-2.1.6.dist-info/zip-safe
