Metadata-Version: 1.1
Name: sphinx-autodoc-napoleon-typehints
Version: 2.1.6
Summary: Type hints (PEP 484) support for the Sphinx autodoc extension
Home-page: https://github.com/daviskirk/sphinx-autodoc-napoleon-typehints
Author: Davis Kirkendall
Author-email: davis.e.kirkendall@gmail.com
License: MIT
Platform: UNKNOWN
Classifier: Development Status :: 5 - Production/Stable
Classifier: Framework :: Sphinx :: Extension
Classifier: Intended Audience :: Developers
Classifier: License :: OSI Approved :: MIT License
Classifier: Framework :: Sphinx :: Extension
Classifier: Topic :: Documentation :: Sphinx
Classifier: Programming Language :: Python
Classifier: Programming Language :: Python :: 3
Classifier: Programming Language :: Python :: 3.3
Classifier: Programming Language :: Python :: 3.4
Classifier: Programming Language :: Python :: 3.5
